wagtailemoji/__init__.py
wagtailemoji/wagtail_hooks.py
wagtailemoji/static/wagtailemoji/css/wagtailemoji.css
wagtailemoji/static/wagtailemoji/fonts/NotoEmoji-Regular.ttf
wagtailemoji-1.0.2.dist-info/DESCRIPTION.rst
wagtailemoji-1.0.2.dist-info/METADATA
wagtailemoji-1.0.2.dist-info/RECORD
wagtailemoji-1.0.2.dist-info/WHEEL
wagtailemoji-1.0.2.dist-info/metadata.json
wagtailemoji-1.0.2.dist-info/top_level.txt
