Metadata-Version: 2.0
Name: wagtailemoji
Version: 1.0.2
Summary: Add emoji to StreamField.
Home-page: https://github.com/alexgleason/wagtailemoji
Author: Alex Gleason
Author-email: alex@alexgleason.me
License: MIT
Keywords: development
Platform: UNKNOWN
Classifier: Environment :: Web Environment
Classifier: Framework :: Django
Classifier: Intended Audience :: Developers
Classifier: Operating System :: OS Independent
Classifier: Programming Language :: Python
Classifier: Topic :: Internet :: WWW/HTTP
Classifier: Topic :: Internet :: WWW/HTTP :: Dynamic Content
Requires-Dist: Django (>=1.7.1)
Requires-Dist: wagtail (>=1.4.0)
